decision_tree/__init__.py
decision_tree/tree.py
randchain_core/__init__.py
randchain_core/chat.py
randchain_core/config.py
randchain_core/loggings.py
randchain_core/utils.py
sequential/__init__.py
sequential/chain.py
randchain-0.1.4.dist-info/METADATA
randchain-0.1.4.dist-info/WHEEL
randchain-0.1.4.dist-info/top_level.txt
randchain-0.1.4.dist-info/RECORD
