Metadata-Version: 2.4
Name: randchain
Version: 0.1.4
Summary: A flexible Python library for building randomized sequential and decision-tree based chains.
Author-email: Pradeep Kumar Yadav <pydev.pk@gmail.com>
License: MIT Attribution License (Modified)
Project-URL: Homepage, https://github.com/pydevpk/randchain
Project-URL: Repository, https://github.com/pydevpk/randchain
Project-URL: Issues, https://github.com/pydevpk/randchain/issues
Keywords: random,chain,decision,sequence,ai,python
Classifier: Development Status :: 4 - Beta
Classifier: Intended Audience :: Developers
Classifier: Programming Language :: Python :: 3
Classifier: License :: OSI Approved :: MIT License
Classifier: Operating System :: OS Independent
Requires-Python: >=3.10
